pyweed/__init__.py
pyweed/app.icns
pyweed/build_launcher.py
pyweed/clients.py
pyweed/dist_from_events.py
pyweed/event_options.py
pyweed/events_handler.py
pyweed/options.py
pyweed/preferences.py
pyweed/pyweed_core.py
pyweed/pyweed_launcher.py
pyweed/pyweed_utils.py
pyweed/signals.py
pyweed/station_options.py
pyweed/stations_handler.py
pyweed/summary.py
pyweed/tests.py
pyweed/waveforms_handler.py
pyweed/gui/Adapters.py
pyweed/gui/BaseDialog.py
pyweed/gui/ConsoleDialog.py
pyweed/gui/EventOptionsWidget.py
pyweed/gui/LoggingDialog.py
pyweed/gui/MainWindow.py
pyweed/gui/MyDoubleValidator.py
pyweed/gui/MyNumericTableWidgetItem.py
pyweed/gui/MyTableWidgetImageItem.py
pyweed/gui/MyTableWidgetImageWidget.py
pyweed/gui/MyTextEditLoggingHandler.py
pyweed/gui/OptionsWidget.py
pyweed/gui/PreferencesDialog.py
pyweed/gui/PyWeedGUI.py
pyweed/gui/Seismap.py
pyweed/gui/SpinnerWidget.py
pyweed/gui/SplashScreenHandler.py
pyweed/gui/StationOptionsWidget.py
pyweed/gui/TableItems.py
pyweed/gui/TableWidget.py
pyweed/gui/WaveformDialog.py
pyweed/gui/__init__.py
pyweed/gui/qrc.py
pyweed/gui/uic/EventOptionsWidget.py
pyweed/gui/uic/LoggingDialog.py
pyweed/gui/uic/MainWindow.py
pyweed/gui/uic/MyQt4MplCanvas.py
pyweed/gui/uic/PreferencesDialog.py
pyweed/gui/uic/SpinnerWidget.py
pyweed/gui/uic/StationOptionsWidget.py
pyweed/gui/uic/WaveformDialog.py
pyweed/gui/uic/__init__.py
pyweed-1.0.12.dist-info/licenses/LICENSE
pyweed-1.0.12.dist-info/METADATA
pyweed-1.0.12.dist-info/WHEEL
pyweed-1.0.12.dist-info/entry_points.txt
pyweed-1.0.12.dist-info/top_level.txt
pyweed-1.0.12.dist-info/RECORD
