Metadata-Version: 2.4
Name: pyweed
Version: 1.0.12
Summary: A GUI application for discovering and downloading seismic data
Author-email: Adam Clark <adam.clark@earthscope.org>
Keywords: FDSN,EarthScope,miniSEED,earthquake,seismic data
Classifier: Development Status :: 5 - Production/Stable
Classifier: License :: OSI Approved :: GNU Lesser General Public License v3 (LGPLv3)
Classifier: Environment :: MacOS X
Classifier: Environment :: Win32 (MS Windows)
Classifier: Environment :: X11 Applications :: Qt
Classifier: Intended Audience :: Science/Research
Classifier: Topic :: Scientific/Engineering :: Physics
Classifier: Programming Language :: Python
Classifier: Programming Language :: Python :: 3
Requires-Python: <3.12,>=3.9
License-File: LICENSE
Requires-Dist: numpy
Requires-Dist: basemap
Requires-Dist: matplotlib
Requires-Dist: obspy==1.4.*
Requires-Dist: pillow
Requires-Dist: pyqt5
Requires-Dist: pyproj
Dynamic: license-file
